dito/__init__.py
dito/analysis.py
dito/conversion.py
dito/core.py
dito/data.py
dito/draw.py
dito/exceptions.py
dito/highgui.py
dito/inspection.py
dito/io.py
dito/parallel.py
dito/processing.py
dito/tests.py
dito/utils.py
dito/visual.py
dito/resources/colormaps/plot.png
dito/resources/colormaps/plot2.png
dito/resources/colormaps/colorbrewer/LICENSE.txt
dito/resources/colormaps/colorbrewer/accent.png
dito/resources/colormaps/colorbrewer/blues.png
dito/resources/colormaps/colorbrewer/brbg.png
dito/resources/colormaps/colorbrewer/bugn.png
dito/resources/colormaps/colorbrewer/bupu.png
dito/resources/colormaps/colorbrewer/colorbrewer.json
dito/resources/colormaps/colorbrewer/dark2.png
dito/resources/colormaps/colorbrewer/gnbu.png
dito/resources/colormaps/colorbrewer/greens.png
dito/resources/colormaps/colorbrewer/greys.png
dito/resources/colormaps/colorbrewer/oranges.png
dito/resources/colormaps/colorbrewer/orrd.png
dito/resources/colormaps/colorbrewer/paired.png
dito/resources/colormaps/colorbrewer/pastel1.png
dito/resources/colormaps/colorbrewer/pastel2.png
dito/resources/colormaps/colorbrewer/piyg.png
dito/resources/colormaps/colorbrewer/prgn.png
dito/resources/colormaps/colorbrewer/pubu.png
dito/resources/colormaps/colorbrewer/pubugn.png
dito/resources/colormaps/colorbrewer/puor.png
dito/resources/colormaps/colorbrewer/purd.png
dito/resources/colormaps/colorbrewer/purples.png
dito/resources/colormaps/colorbrewer/rdbu.png
dito/resources/colormaps/colorbrewer/rdgy.png
dito/resources/colormaps/colorbrewer/rdpu.png
dito/resources/colormaps/colorbrewer/rdylbu.png
dito/resources/colormaps/colorbrewer/rdylgn.png
dito/resources/colormaps/colorbrewer/reds.png
dito/resources/colormaps/colorbrewer/set1.png
dito/resources/colormaps/colorbrewer/set2.png
dito/resources/colormaps/colorbrewer/set3.png
dito/resources/colormaps/colorbrewer/spectral.png
dito/resources/colormaps/colorbrewer/ylgn.png
dito/resources/colormaps/colorbrewer/ylgnbu.png
dito-2.13.0.dist-info/LICENSE.txt
dito-2.13.0.dist-info/METADATA
dito-2.13.0.dist-info/WHEEL
dito-2.13.0.dist-info/top_level.txt
dito-2.13.0.dist-info/RECORD
