Metadata-Version: 2.1
Name: dito
Version: 2.13.0
Summary: Yet another toolbox for the daily work with OpenCV under Python
Home-page: https://github.com/dhaase-de/dito
Author: Daniel Haase
License: UNKNOWN
Platform: UNKNOWN
Classifier: License :: OSI Approved :: MIT License
Classifier: Programming Language :: Python :: 3.7
Classifier: Programming Language :: Python :: 3.8
Classifier: Programming Language :: Python :: 3.9
Classifier: Programming Language :: Python :: 3.10
Classifier: Programming Language :: Python :: 3.11
Classifier: Operating System :: OS Independent
Classifier: Topic :: Utilities
License-File: LICENSE.txt
